JavaXiangmuDaquanChuyi/README.md
JavaXiangmuDaquanChuyi/__init__.py
JavaXiangmuDaquanChuyi/__main__.py
JavaXiangmuDaquanChuyi/file.epub
JavaXiangmuDaquanChuyi/index.html
JavaXiangmuDaquanChuyi/css/__init__.py
JavaXiangmuDaquanChuyi/css/annotations.css
JavaXiangmuDaquanChuyi/css/main.css
JavaXiangmuDaquanChuyi/css/normalize.css
JavaXiangmuDaquanChuyi/css/popup.css
JavaXiangmuDaquanChuyi/font/__init__.py
JavaXiangmuDaquanChuyi/font/fontello.eot
JavaXiangmuDaquanChuyi/font/fontello.svg
JavaXiangmuDaquanChuyi/font/fontello.ttf
JavaXiangmuDaquanChuyi/font/fontello.woff
JavaXiangmuDaquanChuyi/img/__init__.py
JavaXiangmuDaquanChuyi/img/annotator-glyph-sprite.png
JavaXiangmuDaquanChuyi/img/annotator-icon-sprite.png
JavaXiangmuDaquanChuyi/img/apple-touch-icon.png
JavaXiangmuDaquanChuyi/img/cancelfullscreen.png
JavaXiangmuDaquanChuyi/img/close.png
JavaXiangmuDaquanChuyi/img/fullscreen.png
JavaXiangmuDaquanChuyi/img/loader.gif
JavaXiangmuDaquanChuyi/img/menu-icon.png
JavaXiangmuDaquanChuyi/img/save.png
JavaXiangmuDaquanChuyi/img/saved.png
JavaXiangmuDaquanChuyi/img/settings-s.png
JavaXiangmuDaquanChuyi/img/settings.png
JavaXiangmuDaquanChuyi/img/star.png
JavaXiangmuDaquanChuyi/js/__init__.py
JavaXiangmuDaquanChuyi/js/epub.js
JavaXiangmuDaquanChuyi/js/epub.min.js
JavaXiangmuDaquanChuyi/js/epub.min.map
JavaXiangmuDaquanChuyi/js/hooks.min.js
JavaXiangmuDaquanChuyi/js/hooks.min.map
JavaXiangmuDaquanChuyi/js/reader.js
JavaXiangmuDaquanChuyi/js/reader.js.map
JavaXiangmuDaquanChuyi/js/reader.min.js
JavaXiangmuDaquanChuyi/js/reader.min.map
JavaXiangmuDaquanChuyi/js/hooks/__init__.py
JavaXiangmuDaquanChuyi/js/hooks/extensions/__init__.py
JavaXiangmuDaquanChuyi/js/hooks/extensions/highlight.js
JavaXiangmuDaquanChuyi/js/libs/__init__.py
JavaXiangmuDaquanChuyi/js/libs/jquery.min.js
JavaXiangmuDaquanChuyi/js/libs/localforage.min.js
JavaXiangmuDaquanChuyi/js/libs/screenfull.js
JavaXiangmuDaquanChuyi/js/libs/screenfull.min.js
JavaXiangmuDaquanChuyi/js/libs/zip.min.js
java_xiangmu_daquan_chuyi-2024.3.5.0.dist-info/METADATA
java_xiangmu_daquan_chuyi-2024.3.5.0.dist-info/WHEEL
java_xiangmu_daquan_chuyi-2024.3.5.0.dist-info/entry_points.txt
java_xiangmu_daquan_chuyi-2024.3.5.0.dist-info/top_level.txt
java_xiangmu_daquan_chuyi-2024.3.5.0.dist-info/RECORD
